realtimex_pyautogui_server/__init__.py
realtimex_pyautogui_server/__main__.py
realtimex_pyautogui_server/server.py
realtimex_pyautogui_server-0.1.4.dist-info/METADATA
realtimex_pyautogui_server-0.1.4.dist-info/WHEEL
realtimex_pyautogui_server-0.1.4.dist-info/entry_points.txt
realtimex_pyautogui_server-0.1.4.dist-info/licenses/LICENSE
realtimex_pyautogui_server-0.1.4.dist-info/RECORD
