Metadata-Version: 2.4
Name: realtimex-pyautogui-server
Version: 0.1.4
Summary: RealTimeX MCP server for deterministic GUI control via PyAutoGUI
Author: RealTimeX
License-Expression: MIT
License-File: LICENSE
Keywords: automation,gui,mcp,pyautogui,realtimex
Requires-Python: >=3.10
Requires-Dist: fastmcp>=2.13.0.2
Requires-Dist: pillow>=12.0.0
Requires-Dist: pyautogui>=0.9.54
